hamilton_sdk/__init__.py
hamilton_sdk/adapters.py
hamilton_sdk/driver.py
hamilton_sdk/api/__init__.py
hamilton_sdk/api/clients.py
hamilton_sdk/api/constants.py
hamilton_sdk/api/projecttypes.py
hamilton_sdk/cli/__init__.py
hamilton_sdk/cli/cli.py
hamilton_sdk/cli/initialize.py
hamilton_sdk/cli/templates/__init__.py
hamilton_sdk/cli/templates/common/.env.jinja2
hamilton_sdk/cli/templates/common/README.md.jinja2
hamilton_sdk/cli/templates/common/requirements.txt.jinja2
hamilton_sdk/cli/templates/common/run.py.jinja2
hamilton_sdk/cli/templates/common/run.sh.jinja2
hamilton_sdk/cli/templates/data_processing/template_data.json
hamilton_sdk/cli/templates/data_processing/components/__init__.py
hamilton_sdk/cli/templates/data_processing/components/_run.py
hamilton_sdk/cli/templates/data_processing/components/common.py
hamilton_sdk/cli/templates/data_processing/components/data_loader.py
hamilton_sdk/cli/templates/data_processing/config/config.json
hamilton_sdk/cli/templates/data_processing/data/order_details.csv
hamilton_sdk/cli/templates/data_processing/data/orders_new.csv
hamilton_sdk/cli/templates/data_processing/data/orders_old.csv
hamilton_sdk/cli/templates/hello_world/template_data.json
hamilton_sdk/cli/templates/hello_world/components/__init__.py
hamilton_sdk/cli/templates/hello_world/components/transforms.py
hamilton_sdk/cli/templates/hello_world/data/signups.csv
hamilton_sdk/cli/templates/hello_world/data/spend.csv
hamilton_sdk/cli/templates/machine_learning/template_data.json
hamilton_sdk/cli/templates/machine_learning/components/__init__.py
hamilton_sdk/cli/templates/machine_learning/components/_run.py
hamilton_sdk/cli/templates/machine_learning/components/feature_transforms.py
hamilton_sdk/cli/templates/machine_learning/components/iris_loader.py
hamilton_sdk/cli/templates/machine_learning/components/model_fitting.py
hamilton_sdk/cli/templates/machine_learning/components/models.py
hamilton_sdk/cli/templates/time_series_feature_engineering/template_data.json
sf_hamilton_sdk-0.8.0.dist-info/METADATA
sf_hamilton_sdk-0.8.0.dist-info/WHEEL
sf_hamilton_sdk-0.8.0.dist-info/entry_points.txt
sf_hamilton_sdk-0.8.0.dist-info/top_level.txt
sf_hamilton_sdk-0.8.0.dist-info/RECORD
