Metadata-Version: 2.1
Name: sf-hamilton-sdk
Version: 0.8.0
Summary: Hamilton SDK for reading and writing to the Hamilton backend APIs that support the UI.
Author-email: Stefan Krawczyk <stefan@dagworks.io>, Elijah ben Izzy <elijah@dagworks.io>
Project-URL: Homepage, https://github.com/dagworks-inc/hamilton/
Project-URL: Bug Reports, https://github.com/dagworks-inc/hamilton/issues
Project-URL: Source, https://github.com/dagworks-inc/hamilton/ui/sdk
Project-URL: Documenation, https://hamilton.dagworks.io/
Keywords: hamilton,dagworks,observability
Classifier: Development Status :: 4 - Beta
Classifier: Intended Audience :: Developers
Classifier: Natural Language :: English
Classifier: License :: OSI Approved :: BSD License
Classifier: Programming Language :: Python :: 3
Classifier: Programming Language :: Python :: 3.8
Classifier: Programming Language :: Python :: 3.9
Classifier: Programming Language :: Python :: 3.10
Classifier: Programming Language :: Python :: 3.11
Requires-Python: <4,>=3.7
Requires-Dist: aiohttp
Requires-Dist: click
Requires-Dist: gitpython
Requires-Dist: jinja2
Requires-Dist: loguru
Requires-Dist: posthog
Requires-Dist: requests
Requires-Dist: sf-hamilton>=1.43.0
Requires-Dist: sqlglot
Provides-Extra: test
Requires-Dist: ibis-framework; extra == "test"
Requires-Dist: langchain_core; extra == "test"
Requires-Dist: numpy<2; extra == "test"
Requires-Dist: polars; extra == "test"
Requires-Dist: pyarrow; extra == "test"
Requires-Dist: pyarrow_hotfix; extra == "test"
Requires-Dist: pydantic; extra == "test"
Requires-Dist: pyspark; extra == "test"
Requires-Dist: pytest; extra == "test"
Requires-Dist: ray; extra == "test"
